dtb_tools/__init__.py
dtb_tools/common/__init__.py
dtb_tools/common/decorator.py
dtb_tools/common/err.py
dtb_tools/common/container/BlockValue.py
dtb_tools/common/container/__init__.py
dtb_tools/common/ctx/__init__.py
dtb_tools/common/ctx/daemon.py
dtb_tools/common/json_/__init__.py
dtb_tools/common/json_/model.py
dtb_tools-0.0.15.dist-info/METADATA
dtb_tools-0.0.15.dist-info/WHEEL
dtb_tools-0.0.15.dist-info/top_level.txt
dtb_tools-0.0.15.dist-info/RECORD
