Metadata-Version: 2.1
Name: dtb-tools
Version: 0.0.15
Summary: python tools
Home-page: https://github.com/DaoBillTang/py_tools
Author: dtb
Author-email: 1750352866@qq.com
License: MIT Licence
Keywords: pytools container
Platform: any
